xaal/__init__.py
xaal/schemas/__init__.py
xaal/schemas/dev_builder.py
xaal/schemas/devices.py
xaal_schemas-0.6.dist-info/METADATA
xaal_schemas-0.6.dist-info/WHEEL
xaal_schemas-0.6.dist-info/top_level.txt
xaal_schemas-0.6.dist-info/RECORD
